citiespy-0.6.13.dist-info/METADATA
citiespy-0.6.13.dist-info/WHEEL
citiespy.libs/libgcc_s-0366c7ba.so.1
citiespy/__init__.py
citiespy/__init__.pyi
citiespy/citiespy.cpython-314t-arm-linux-musleabihf.so
citiespy/py.typed
citiespy-0.6.13.dist-info/RECORD
