Metadata-Version: 2.4
Name: citiespy
Version: 0.6.13
Classifier: Programming Language :: Rust
Classifier: Programming Language :: Python :: Implementation :: CPython
Classifier: Programming Language :: Python :: 3.10
Classifier: Programming Language :: Python :: 3.11
Classifier: Programming Language :: Python :: 3.12
Classifier: Programming Language :: Python :: 3.13
Classifier: Programming Language :: Python :: 3.14
Summary: Cities.
Requires-Python: >=3.10
Project-URL: Source Code, https://github.com/ringsaturn/go-cities.json
Project-URL: Issues, https://github.com/ringsaturn/go-cities.json/issues
Project-URL: Documentation, https://github.com/ringsaturn/go-cities.json
